source_rki_covid/__init__.py
source_rki_covid/run.py
source_rki_covid/schemas/TODO.md
source_rki_covid/schemas/german_history_deaths.json
source_rki_covid/schemas/german_history_frozen_incidence.json
source_rki_covid/schemas/german_history_hospitalization.json
source_rki_covid/schemas/german_history_incidence.json
source_rki_covid/schemas/german_history_recovered.json
source_rki_covid/schemas/germany.json
source_rki_covid/schemas/germany_age_groups.json
source_rki_covid/schemas/germany_history_cases.json
source_rki_covid/schemas/germany_states.json
source_rki_covid/schemas/germany_states_age_groups.json
source_rki_covid/schemas/states_history_cases.json
source_rki_covid/schemas/states_history_deaths.json
source_rki_covid/schemas/states_history_frozen_incidence.json
source_rki_covid/schemas/states_history_hospitalization.json
source_rki_covid/schemas/states_history_incidence.json
source_rki_covid/schemas/states_history_recovered.json
source_rki_covid/source.py
source_rki_covid/spec.json
airbyte_source_rki_covid-0.1.41.dist-info/METADATA
airbyte_source_rki_covid-0.1.41.dist-info/WHEEL
airbyte_source_rki_covid-0.1.41.dist-info/entry_points.txt
airbyte_source_rki_covid-0.1.41.dist-info/RECORD
